birds_bi/__init__.py
birds_bi/py.typed
birds_bi/db/__init__.py
birds_bi/db/clone_database.py
birds_bi/db/models.py
birds_bi/db/sql_execution.py
birds_bi/engine/__init__.py
birds_bi/engine/component_relations/__init__.py
birds_bi/engine/component_relations/linked_facts.py
birds_bi/engine/component_relations/linked_stage_tables.py
birds_bi/engine/deploy_dwh/__init__.py
birds_bi/engine/deploy_dwh/deploy_component.py
birds_bi/engine/deploy_dwh/deploy_dwh.py
birds_bi/engine/deploy_dwh/deploy_staging.py
birds_bi/engine/deploy_dwh/models.py
birds_bi/engine/deploy_dwh/deployment_scripts/__init__.py
birds_bi/engine/deploy_dwh/deployment_scripts/add_dwh_component.py
birds_bi/engine/deploy_dwh/deployment_scripts/column_metadata.py
birds_bi/engine/deploy_dwh/deployment_scripts/deploy.py
birds_bi/engine/deploy_dwh/deployment_scripts/dwh_deployment.py
birds_bi/engine/deploy_dwh/deployment_scripts/fact_dimension_joins.py
birds_bi/engine/deploy_dwh/deployment_scripts/manual_mode.py
birds_bi/engine/deploy_dwh/deployment_scripts/post_deployment.py
birds_bi/engine/deploy_dwh/deployment_scripts/pre_deployment.py
birds_bi/engine/deploy_dwh/deployment_scripts/queries_and_aliases.py
birds_bi/engine/deploy_dwh/deployment_scripts/query_columns.py
birds_bi/engine/deploy_dwh/deployment_scripts/stage_table_indexes.py
birds_bi/engine/deploy_dwh/deployment_scripts/start_logging.py
birds_bi/engine/deploy_dwh/deployment_scripts/stop_logging.py
birds_bi/engine/deploy_dwh/deployment_scripts/table_indexes.py
birds_bi/engine/deploy_dwh/deployment_scripts/validate_columns.py
birds_bi/engine/deploy_dwh/deployment_scripts/validate_query.py
birds_bi/engine/process_dwh/__init__.py
birds_bi/engine/process_dwh/process_dwh.py
birds_bi/engine/process_dwh/process_dwh_component.py
birds_bi/git/__init__.py
birds_bi/git/changes.py
birds_bi/git/models.py
birds_bi/repo/__init__.py
birds_bi/repo/component.py
birds_bi/repo/models.py
birds_bi/repo/repository.py
birds_bi/sql/__init__.py
birds_bi/sql/create_scripts.py
birds_bi-0.1.10.dist-info/licenses/LICENSE
birds_bi-0.1.10.dist-info/METADATA
birds_bi-0.1.10.dist-info/WHEEL
birds_bi-0.1.10.dist-info/top_level.txt
birds_bi-0.1.10.dist-info/RECORD
