Metadata-Version: 2.4
Name: birds_bi
Version: 0.1.10
Summary: Birds BI python libary to help you automate repetitive tasks.
Author-email: Jan Willem Schipper <janwillem.schipper@9altitudes.com>
License: MIT
Project-URL: Homepage, https://dev.azure.com/birdsjanwillem/Python%20Birds%20Libary
Requires-Python: >=3.13
License-File: LICENSE
Requires-Dist: pandas>=2.0
Requires-Dist: pyodbc>=5.0
Requires-Dist: pythonnet>=3.0
Requires-Dist: sqlparse>=0.4.0
Provides-Extra: test
Requires-Dist: pytest>=7.4.0; extra == "test"
Requires-Dist: pytest-cov>=4.1.0; extra == "test"
Dynamic: license-file
